README.rst
setup.py
drivigo_api_client/__init__.py
drivigo_api_client/base.py
drivigo_api_client/exceptions.py
drivigo_api_client/http_codes.py
drivigo_api_client/version.py
drivigo_api_client.egg-info/PKG-INFO
drivigo_api_client.egg-info/SOURCES.txt
drivigo_api_client.egg-info/dependency_links.txt
drivigo_api_client.egg-info/requires.txt
drivigo_api_client.egg-info/top_level.txt
drivigo_api_client/sync/__init__.py
drivigo_api_client/sync/base.py
drivigo_api_client/sync/resources.py