Metadata-Version: 1.1
Name: drivigo-api-client
Version: 1.0.7
Summary: Client for Drivigo API
Home-page: https://bitbucket.org/drivigo/api-client
Author: Georgy Kutsurua
Author-email: g.kutsurua@gmail.com
License: BSD
Keywords: API,Cars,Automobiles,Auto,Specs,Drivigo
Platform: linux
Classifier: Environment :: Web Environment
Classifier: Intended Audience :: Developers
Classifier: License :: OSI Approved :: MIT License
Classifier: Operating System :: OS Independent
Classifier: Programming Language :: Python
Classifier: Topic :: Internet :: WWW/HTTP
Classifier: Topic :: Software Development :: Libraries
